satnogsdecoders/__init__.py
satnogsdecoders/_version.py
satnogsdecoders/decode_frame.py
satnogsdecoders/decode_multiple.py
satnogsdecoders/decoder/__init__.py
satnogsdecoders/decoder/aausat4.py
satnogsdecoders/decoder/acrux1.py
satnogsdecoders/decoder/armadillo.py
satnogsdecoders/decoder/ax25frames.py
satnogsdecoders/decoder/ax25monitor.py
satnogsdecoders/decoder/bisonsat.py
satnogsdecoders/decoder/bugsat1.py
satnogsdecoders/decoder/cas4.py
satnogsdecoders/decoder/csim.py
satnogsdecoders/decoder/cspheader.py
satnogsdecoders/decoder/cubebel1.py
satnogsdecoders/decoder/cubesatsim.py
satnogsdecoders/decoder/elfin.py
satnogsdecoders/decoder/entrysat.py
satnogsdecoders/decoder/equisat.py
satnogsdecoders/decoder/eshail2.py
satnogsdecoders/decoder/fox.py
satnogsdecoders/decoder/irazu.py
satnogsdecoders/decoder/irvine.py
satnogsdecoders/decoder/lightsail2.py
satnogsdecoders/decoder/minxss.py
satnogsdecoders/decoder/mxl.py
satnogsdecoders/decoder/mysat.py
satnogsdecoders/decoder/origamisat1.py
satnogsdecoders/decoder/pwsat2.py
satnogsdecoders/decoder/qbee.py
satnogsdecoders/decoder/siriussat.py
satnogsdecoders/decoder/skcube.py
satnogsdecoders/decoder/strand.py
satnogsdecoders/decoder/us6.py
satnogsdecoders/decoder/uwe4.py
satnogsdecoders/process/__init__.py
satnogsdecoders/process/elfin_pp.py
tests/__init__.py
tests/shared_methods.py
tests/test_elfin_pp.py
tests/test_entrysat.py
tests/test_equisat.py
satnogsdecoders-0.16.1.dist-info/LICENSE
satnogsdecoders-0.16.1.dist-info/METADATA
satnogsdecoders-0.16.1.dist-info/WHEEL
satnogsdecoders-0.16.1.dist-info/entry_points.txt
satnogsdecoders-0.16.1.dist-info/top_level.txt
satnogsdecoders-0.16.1.dist-info/RECORD
