Metadata-Version: 2.1
Name: satnogsdecoders
Version: 0.16.1
Summary: SatNOGS Decoders
Home-page: https://gitlab.com/librespacefoundation/satnogs/satnogs-decoders
Author: SatNOGS project
Author-email: dev@satnogs.org
License: AGPLv3
Platform: UNKNOWN
Classifier: Development Status :: 4 - Beta
Classifier: Environment :: Console
Classifier: Intended Audience :: Telecommunications Industry
Classifier: Intended Audience :: Science/Research
Classifier: License :: OSI Approved :: GNU Affero General Public License v3
Classifier: Operating System :: POSIX :: Linux
Classifier: Programming Language :: Python :: 2.7
Classifier: Programming Language :: Python :: 3.6
Classifier: Topic :: Communications :: Ham Radio
Requires-Dist: kaitaistruct (~=0.8.0)
Requires-Dist: enum34 (~=1.1.0)
